aimo/__init__.py
AIMOAnswers-0.0.1.dist-info/LICENSE
AIMOAnswers-0.0.1.dist-info/METADATA
AIMOAnswers-0.0.1.dist-info/WHEEL
AIMOAnswers-0.0.1.dist-info/top_level.txt
AIMOAnswers-0.0.1.dist-info/RECORD
