Metadata-Version: 2.1
Name: AIMOAnswers
Version: 0.0.1
Summary: Contains the answers (in python form) for AIMO
Home-page: https://github.com/ActuallyHappening/AIMO
Author: Smartguy88
Author-email: ActuallyHappening@gmail.com
Platform: unix
Platform: linux
Platform: osx
Platform: cygwin
Platform: win32
Classifier: Programming Language :: Python :: 3
Classifier: Programming Language :: Python :: 3 :: Only
Classifier: Programming Language :: Python :: 3.10
Classifier: Programming Language :: Python :: 3.9
Requires-Python: >=3.9
License-File: LICENSE
